pytest_cases/__init__.py
pytest_cases/_version.py
pytest_cases/case_funcs.py
pytest_cases/case_parametrizer_new.py
pytest_cases/common_mini_six.py
pytest_cases/common_others.py
pytest_cases/common_pytest.py
pytest_cases/common_pytest_lazy_values.py
pytest_cases/common_pytest_marks.py
pytest_cases/filters.py
pytest_cases/fixture__creation.py
pytest_cases/fixture_core1_unions.py
pytest_cases/fixture_core2.py
pytest_cases/fixture_parametrize_plus.py
pytest_cases/pep380.py
pytest_cases/pep492.py
pytest_cases/pep525.py
pytest_cases/plugin.py
pytest_cases/py.typed
pytest_cases-3.9.1.dist-info/licenses/LICENSE
pytest_cases-3.9.1.dist-info/METADATA
pytest_cases-3.9.1.dist-info/WHEEL
pytest_cases-3.9.1.dist-info/entry_points.txt
pytest_cases-3.9.1.dist-info/top_level.txt
pytest_cases-3.9.1.dist-info/RECORD
