Metadata-Version: 2.4
Name: pytest-cases
Version: 3.9.1
Summary: Separate test code from test cases in pytest.
Home-page: https://github.com/smarie/python-pytest-cases
Download-URL: https://github.com/smarie/python-pytest-cases/tarball/3.9.1
Author: Sylvain MARIE <sylvain.marie@se.com>
Maintainer: Sylvain MARIE <sylvain.marie@se.com>
License: BSD 3-Clause
Keywords: pytest test case testcase test-case decorator parametrize parameter data dataset file separate concerns lazy fixture union
Classifier: Development Status :: 5 - Production/Stable
Classifier: Intended Audience :: Developers
Classifier: License :: OSI Approved :: BSD License
Classifier: Topic :: Software Development :: Libraries :: Python Modules
Classifier: Topic :: Software Development :: Testing
Classifier: Programming Language :: Python
Classifier: Programming Language :: Python :: 3.9
Classifier: Programming Language :: Python :: 3.10
Classifier: Programming Language :: Python :: 3.11
Classifier: Programming Language :: Python :: 3.12
Classifier: Programming Language :: Python :: 3.14
Classifier: Framework :: Pytest
License-File: LICENSE
Requires-Dist: decopatch
Requires-Dist: makefun>=1.15.1
Requires-Dist: packaging
Requires-Dist: pytest
Dynamic: download-url
Dynamic: license-file
